pas.plugins.imio-3.0.0-py3.12-nspkg.pth
pas/plugins/imio/__init__.py
pas/plugins/imio/configure.zcml
pas/plugins/imio/integration.py
pas/plugins/imio/interfaces.py
pas/plugins/imio/login.py
pas/plugins/imio/logout.py
pas/plugins/imio/plugin.py
pas/plugins/imio/setuphandlers.py
pas/plugins/imio/testing.py
pas/plugins/imio/upgrades.py
pas/plugins/imio/user.py
pas/plugins/imio/useridentities.py
pas/plugins/imio/useridfactories.py
pas/plugins/imio/utils.py
pas/plugins/imio/zmi.zpt
pas/plugins/imio/browser/__init__.py
pas/plugins/imio/browser/add_plugin.pt
pas/plugins/imio/browser/authentic.pt
pas/plugins/imio/browser/configure.zcml
pas/plugins/imio/browser/usergroups.py
pas/plugins/imio/browser/usergroups_usersoverview.py
pas/plugins/imio/browser/view.py
pas/plugins/imio/browser/overrides/.gitkeep
pas/plugins/imio/browser/overrides/Products.CMFPlone.skins.plone_login.login_form.cpt
pas/plugins/imio/browser/overrides/Products.CMFPlone.skins.plone_login.login_form.cpt.metadata
pas/plugins/imio/browser/static/arrow.svg
pas/plugins/imio/browser/static/loginpage.css
pas/plugins/imio/browser/static/logo-agent.svg
pas/plugins/imio/browser/static/logo-usager.svg
pas/plugins/imio/browser/templates/zope_login.pt
pas/plugins/imio/locales/pas.plugins.imio.pot
pas/plugins/imio/locales/update.sh
pas/plugins/imio/locales/en/LC_MESSAGES/pas.plugins.imio.po
pas/plugins/imio/locales/fr/LC_MESSAGES/pas.plugins.imio.po
pas/plugins/imio/profiles/base/browserlayer.xml
pas/plugins/imio/profiles/base/metadata.xml
pas/plugins/imio/profiles/base/registry.xml
pas/plugins/imio/profiles/plone4/componentregistry.xml
pas/plugins/imio/profiles/plone4/jsregistry.xml
pas/plugins/imio/profiles/plone4/metadata.xml
pas/plugins/imio/profiles/plone5/metadata.xml
pas/plugins/imio/profiles/testing4/metadata.xml
pas/plugins/imio/profiles/testing4/registry.xml
pas/plugins/imio/profiles/testing5/metadata.xml
pas/plugins/imio/profiles/testing5/registry.xml
pas/plugins/imio/profiles/uninstall/browserlayer.xml
pas_plugins_imio-3.0.0.dist-info/licenses/LICENSE.GPL
pas_plugins_imio-3.0.0.dist-info/licenses/LICENSE.rst
pas_plugins_imio-3.0.0.dist-info/METADATA
pas_plugins_imio-3.0.0.dist-info/WHEEL
pas_plugins_imio-3.0.0.dist-info/entry_points.txt
pas_plugins_imio-3.0.0.dist-info/namespace_packages.txt
pas_plugins_imio-3.0.0.dist-info/top_level.txt
pas_plugins_imio-3.0.0.dist-info/RECORD
